[
  {
    "long_url": "https://www.google.com",
    "short_code": "gfv02A",
    "userid": "s.satyaki98@gmail.com",
    "sysdate": "2026-04-09T09:30:58.348977"
  },
  {
    "long_url": "https://www.facebook.com",
    "short_code": "Txsm4A",
    "userid": "s.satyaki98@gmail.com",
    "sysdate": "2026-04-09T09:31:32.697476"
  },
  {
    "long_url": "https://www.github.com",
    "short_code": "T6Gijg",
    "userid": "s.satyaki98@gmail.com",
    "sysdate": "2026-04-09T09:31:41.465883"
  },
  {
    "long_url": "https://powerpoint.cloud.microsoft/open/onedrive/?docId=F34033FA1F1357B7%21s5ca2b5e3fd234e82bf7030d7270cb957&driveId=F34033FA1F1357B7",
    "short_code": "v3iF5Q",
    "userid": "s.satyaki98@gmail.com",
    "sysdate": "2026-04-09T18:14:51.228960"
  }
]